django_sloop/__init__.py
django_sloop/admin.py
django_sloop/apps.py
django_sloop/exceptions.py
django_sloop/handlers.py
django_sloop/models.py
django_sloop/serializers.py
django_sloop/settings.py
django_sloop/tasks.py
django_sloop/tests.py
django_sloop/urls.py
django_sloop/utils.py
django_sloop/views.py
django_sloop/migrations/0001_initial.py
django_sloop/migrations/0002_change_meta.py
django_sloop/migrations/__init__.py
django_sloop/templates/django_sloop/push_notification.html
django_sloop-1.0.7.dist-info/LICENSE
django_sloop-1.0.7.dist-info/METADATA
django_sloop-1.0.7.dist-info/WHEEL
django_sloop-1.0.7.dist-info/top_level.txt
django_sloop-1.0.7.dist-info/RECORD
